{
  "field": "검사실운영",
  "chunk": 8,
  "total_chunks": 18,
  "items": [
    {
      "code": "01.606.024",
      "type": "B",
      "points": 1,
      "question": "장비이상 등의 문제 발생 시 자동검증과정을 즉시 중지시킬 수 있는 절차를 가지고 있는가?",
      "guidance": "지침서 수행되며를 확인한다.\n자동검증을 하지 않는 검사실의 경우에 '해당없음'으로 평가한다."
    },
    {
      "code": "01.607.014",
      "type": "B",
      "points": 1,
      "question": "동일 검사를 여러 기기로 수행하는 경우, 검사를 수행한 기기를 구별할 수 있는가?",
      "guidance": "없음"
    },
    {
      "code": "01.607.016",
      "type": "B",
      "points": 1,
      "question": "화재, 천재지변, 소프트웨어와 하드웨어 고장 등의 경우에 데이터와 장비의 보존을 위한 대비가 적절히 수립되어 있는가?",
      "guidance": "심사원은 이를 확인해야 한다. 지침이 없거나 불충분한 경우에는 '0점'으로 평가한다.\n재난의 확률을 절차, 정기적인 데이터 백업 시 작업 규모, off-site 백업 장소, 백업된 미디어로부터 정보를 복구하는 절차 등이 포함되어야 한다.\n자료 파일을 백업으로 즉시 복구한 후 무작위로 전후의 자료를 비교하거나 혹은 유사한 절차에 의해 그 자료의 안정성을 확인하여야 한다.\n하드웨어나 소프트웨어의 변경 사례는 이러한 지침서의 재검토 및 갱신이 필요하다."
    },
    {
      "code": "01.608.012",
      "type": "B",
      "points": 1,
      "question": "중요한 시스템 이상 등을 보고받는 책임자가 검사실 내부 인원으로 지정되어 있는가?",
      "guidance": "없음"
    },
    {
      "code": "01.608.015",
      "type": "B",
      "points": 1,
      "question": "LIS 프로그램을 설치, 변경 및 수정 후에 기능이 정상적으로 작동하는지 확인하고 프로그램을 사용하는 지침 및 기록이 있는가?",
      "guidance": "검사실 과장 또는 위임받은 자가 새로 설치, 변경, 수정된 LIS 프로그램의 사용을 승인한 기록이 있어야 한다."
    },
    {
      "code": "01.608.017",
      "type": "B",
      "points": 1,
      "question": "LIS 프로그램이 변경되거나 새로운 프로그램이 설치될 때 사용자가 모두 교육을 받았다는 기록이 있는가?",
      "guidance": "없음"
    },
    {
      "code": "01.608.019",
      "type": "B",
      "points": 1,
      "question": "LIS 프로그램의 수정 및 업그레이드가 기록되는가?",
      "guidance": "Source code를 기관 내에 가지고 있도록 권장한다."
    },
    {
      "code": "01.701.040",
      "type": "B",
      "points": 1,
      "question": "운영내규 및 조직도가 있는가?",
      "guidance": "모든 검사실 직원의 책임, 권한, 직무 등을 규정한 직무기술서와 조직도를 비치하고 공유해야 한다.\n검사실 직무별 책임자의 임명과 조직도를 확인하며, 그에 대한 절차가 문서화되어 있어야 한다.\n조직도에는 기관장, 검사실 과장, 직무별 책임자 등의 관계가 포함되어야 한다."
    },
    {
      "code": "01.701.060",
      "type": "B",
      "points": 1,
      "question": "검사실 혹은 검사실이 속한 기관에 문서화된 인사 관리규정이 있는가?",
      "guidance": "검사실 혹은 검사실이 속한 기관의 인사관리규정(근무시간 등)을 확인한다.\n검사실 혹은 검사실이 속한 기관의 규정에 맞게 인력 및 직무 관리(통상근무, 야간 및 휴일 근무, 초과근무 등)가 이루어져야 한다."
    },
    {
      "code": "01.701.080",
      "type": "B",
      "points": 1,
      "question": "모든 검사실 직원에 대한 인사관리 기록이 유지되고 있는가?",
      "guidance": "인사관리기록에 다음이 포함되어야 한다.\n(1) 학력 및 경력\n(2) 면허증 사본 또는 졸업증서\n(3) 진급(승급) 기록"
    }
  ]
}