{
  "field": "수혈의학",
  "chunk": 19,
  "total_chunks": 29,
  "items": [
    {
      "code": "46.610.462",
      "type": "B",
      "points": 1,
      "question": "혈액 및 혈액제제를 운반하기 전 수송이 적합한 상태(혈액의 상태, 혈액운반상자의 외형 등)인지 확인하는가?",
      "guidance": "없음"
    },
    {
      "code": "46.610.464",
      "type": "B",
      "points": 1,
      "question": "적합한 냉매제를 사용하여 혈액제제별 운반 온도를 준수하는가?",
      "guidance": "없음"
    },
    {
      "code": "46.610.466",
      "type": "B",
      "points": 1,
      "question": "혈액운반상자에 [취급상의 주의점]과 [혈액제제명]을 표시하는가?",
      "guidance": "없음"
    },
    {
      "code": "46.610.468",
      "type": "B",
      "points": 1,
      "question": "혈액운반상자 전량에 대하여 냉매제가 지침대로 사용되었는지를 모니터링하는가?",
      "guidance": "없음"
    },
    {
      "code": "46.610.470",
      "type": "B",
      "points": 1,
      "question": "수거혈액 인수자는 [채혈내역서]의 내용과 혈액실물 및 검체수량이 일치하는지 확인 후 [입고시각]을 기록하고 인수자란에 서명하는가?",
      "guidance": "없음"
    },
    {
      "code": "46.610.472",
      "type": "B",
      "points": 1,
      "question": "검체(NAT)수송시 적정 냉매제를 사용하고 [검체운송 인계인수서]를 작성하고 서명하는가?",
      "guidance": "없음"
    },
    {
      "code": "46.610.474",
      "type": "B",
      "points": 1,
      "question": "혈액수거시 채혈내역서, 혈액실물, 헌혈기록카드, 혈액검체 등이 정확하게 수거되는 것을 확인하는가?",
      "guidance": "없음"
    },
    {
      "code": "46.610.476",
      "type": "B",
      "points": 1,
      "question": "수송 중인 혈액운반상자 내부온도를 제제별로 월 1회 이상 정기적으로 측정하여 혈액제제가 적정온도로 유지되는지를 점검하는가?",
      "guidance": "없음"
    },
    {
      "code": "46.611.462",
      "type": "B",
      "points": 1,
      "question": "혈액입고 전산입력시 차량, 장소, 혈액백 종류, 말라리아 관련 정보 등을 정확히 입력하고 확인하는가?",
      "guidance": "없음"
    },
    {
      "code": "46.611.464",
      "type": "B",
      "points": 1,
      "question": "원료혈액 및 성분별로 제제된 혈액을 제제팀에서 인수시, 수량을 확인하고 인계인수서에 서명하며 불일치 발생시 문제를 해결하는 업무절차를 갖추고 있는가?",
      "guidance": "없음"
    }
  ]
}