{
  "field": "수혈의학",
  "chunk": 8,
  "total_chunks": 29,
  "items": [
    {
      "code": "43.220.411",
      "type": "B",
      "points": 1,
      "question": "대한수혈학회, 보건복지부, 질병관리본부에서 공동 발행한 '수혈가이드라인' 혹은 기관 수혈지침서를 혈액은행에 비치하고, 주요 임상과에 안내하여있는가?",
      "guidance": "인쇄한 책자가 구비되어 있거나 컴퓨터 본이 혈액은행 컴퓨터에 있는지 확인한다.\n구비된 '수혈가이드라인' 가장 최근 버전(version)이 아닌 경우 반영을 감점한다.\n임상과에 안내를 한 공문이나 이메일에 대한 기록이 구비되어야 하고, 없으면 '아니오'로 평가한다."
    },
    {
      "code": "43.280.100",
      "type": "B",
      "points": 2,
      "question": "수혈관리위원회가 구성되어 있으며, 진단검사의학과 전문의가 위원회 업무에 적극 참여하고 있는가?",
      "guidance": "수혈관리위원회는 위원장 1명을 포함한 7명 이상 15명 이하의 위원으로 구성한다.\n수혈관리위원회의 위원장은 해당 의료기관의 장으로 하고, 부위원장은 위원 중에서 위원장이 지명한다.\n수혈관리위원회의 위원은 다음 각 호의 사람이 된다.\n(1) 진료부서의 장\n(2) 간호부서의 장\n(3) 수혈관리실의 장(수혈관리실을 설치한 경우만 해당한다)\n(4) 수혈관리 분야에 관한 학식과 경험이 풍부한 사람 중에서 위원장이 위촉하는 사람"
    },
    {
      "code": "43.280.110",
      "type": "B",
      "points": 2,
      "question": "수혈관리위원회 회의는 반기별로 1회 이상 개최하는가?",
      "guidance": "수혈관리위원회는 다음 각 호의 사항을 심의한다.\n(1) 수혈관리계획의 수립 및 시행\n(2) 안전하고 적정한 수혈관리를 위한 자체 규정\n(3) 수혈용 혈액의 보관량·사용량·폐기량의 적정성\n(4) 수혈용 혈액의 안정적인 수급 방안\n(5) 수혈 관련 부작용의 예방·대응방법\n(6) 수혈 관련 교육 및 홍보 방법\n(7) 그 밖에 안전하고 적정한 혈액 사용을 위하여 보건복지부장관이 정하는 사항\n회의록을 작성·보관하여야 한다."
    },
    {
      "code": "43.280.120",
      "type": "B",
      "points": 2,
      "question": "수혈관리실을 설치 및 운영하고 있는가?",
      "guidance": "수혈관리실은 다음 각 호의 업무를 수행한다.\n(1) 수혈용 혈액의 보관·사용·폐기 현황의 관리\n(2) 수혈 관련 자료의 수집·분석 및 평가\n(3) 수혈의 적정성에 대한 평가\n(4) 수혈 관련 부작용의 발생 감시 및 대응\n(5) 수혈 관련 교육 및 홍보\n(6) 그 밖에 수혈관리에 필요한 업무\n기관 내 조직도와 규정을 확인한다.\n혈액관리법 시행규칙 제12조의3에 해당하는 기관만 심사한다."
    },
    {
      "code": "43.280.130",
      "type": "B",
      "points": 2,
      "question": "수혈관리실에는 적정한 인력이 근무하고 있으며, 1명 이상의 전담 인력이 있는가?",
      "guidance": "수혈관리실에 다음 각 호의 인력을 두고, 이 중 1명 이상은 전담 근무해야 한다.\n(1) 수혈관리에 경험과 지식이 있는 의사 1명 이상\n(2) 수혈관리에 관한 경험과 지식이 있는 간호사 1명 이상\n(3) 수혈관리에 관한 경험과 지식이 있는 임상병리사 1명 이상 또는 의료기관의 장이 수혈관리를 위하여 필요하다고 인정하는 사람 1명 이상\n수혈관리실에서 근무하는 사람은 혈액관리법 시행규칙 별표 5의2에서 정한 교육기준에 따라 매년 8시간 이상 관련 교육을 받아야 한다.\n혈액관리법 시행규칙 제12조의3에 해당하는 기관만 심사한다.\n참고자료: 혈액관리법 시행규칙(제12조의5)"
    },
    {
      "code": "43.601.401",
      "type": "B",
      "points": 4,
      "question": "혈액은행은 수혈용 혈액의 보관 및 해동을 위하여 다음의 장비를 구비하고 있는가?",
      "guidance": "(1) 혈액전용 냉장고\n(2) 혈액전용 냉동고\n(3) 혈소판교반기\n(4) 혈장해동기\n혈액전용냉장고, 혈액전용냉동고, 혈소판교반기에는 모두 온도감시·기록·경보장치가 있어야 한다.\n수혈용 혈액제제가 기타 시약이나 물품과 같이 보관되는 경우 '아니오'로 평가한다.\n혈장해동기가 아닌 해동용 온수조의 경우 혈장제제의 해동에만 사용되고, 기타 검사에 사용되지 않는 경우에만 혈장해동기를 구비한 것으로 인정한다.\n기관에서 수혈하는 혈액제제에 필요한 장비를 모두 구비하고 있는 경우 만점을 부여한다."
    },
    {
      "code": "43.601.430",
      "type": "B",
      "points": 2,
      "question": "혈액은행용 냉장고, 냉동고 및 혈소판 교반장치의 온도는 24시간 측정되거나, 그렇지 않을 경우에는 최소한 4시간 마다 온도를 측정, 기록하며, 허용범위는 설정되어 있는가?",
      "guidance": "장비에 장착되어 있는 온도계가 있더라도 표준온도계로 검증된 별도의 온도계를 설치해야 하며, 장비 내에 두 개의 probe가 있다면 한 개는 표준온도계로 검증해야 한다.\n두 개의 온도를 매일 비교 확인하고 차이를 기록하여야 한다."
    },
    {
      "code": "43.601.435",
      "type": "B",
      "points": 2,
      "question": "혈액은행용 냉장고, 냉동고 및 혈소판 교반장치에는 온도를 24시간 감시하는 경고음장치가 설치되어 있는가?",
      "guidance": "혈액을 보관하는 모든 냉장고, 냉동고 및 혈소판 교반장치는 경고장치를 가지고 있어야 하며, 경고음이 작동하는 최고 및 최저 온도는 허용범위내에서 적정하게 설정되어야 한다.\n담당 임상병리사는 경고음장치가 어떻게 작동되는지 설명할 수 있어야 하며, 경고음 작동을 주기적으로 검토하고 점검한 기록이 있어야 한다.\n실제로 경고음이 작동한 경우 조치를 취하고 그 결과를 기록으로 남겨야 한다."
    },
    {
      "code": "43.601.440",
      "type": "B",
      "points": 2,
      "question": "혈액은행용 냉장고와 냉동고는 전원이 차단되어도 경고장치가 계속 작동하는가?",
      "guidance": "경고음장치를 위한 배터리가 있는지를 관찰하고 이에 대한 주기적인 점검이 있었는지를 확인한다."
    },
    {
      "code": "43.602.401",
      "type": "B",
      "points": 2,
      "question": "혈액제제용 방사선조사기가 있다면 이에 대한 법적 점도관리 절차와 타이머, turntable 확인, calibration 및 누선량 점검을 포함한 점검을 주기적으로 시행하며, 그 기록을 보관하고 있는가?",
      "guidance": "없음"
    }
  ]
}