{
  "field": "수혈의학",
  "chunk": 4,
  "total_chunks": 29,
  "items": [
    {
      "code": "40.504.300",
      "type": "B",
      "points": 1,
      "question": "모든 온도관련 기기(냉장고, 냉동고 등)에는 온도의 허용범위가 정해져 있는가?",
      "guidance": "장비별 온도 점검표에 허용범위가 표시되어 있어야 한다.\n온도관련 기기의 온도가 허용범위를 벗어났을 경우, 취하여야 할 조치 등에 관한 지침 및 시행기록이 있어야 한다(수정조치 내용에는 냉장고나 냉동고에 보관하였던 정도관리물질, 시약, 보정물질 등에 대한 평가기록이 있어야 한다.).\n제조사의 규정에 맞게 시약이나 검체 상태가 영향을 받지 않는 범위내에서 온도가 유지되고 기록되고 있는지에 대한 지침과 기록을 확인한다."
    },
    {
      "code": "40.506.020",
      "type": "B",
      "points": 1,
      "question": "렌즈가 저배율, 고배율 등에서 깨끗하고 정확하게 보이는 지에 대한 정기적인 점검기록부가 있는가?",
      "guidance": "현미경 점검 기록부를 확인한다. 현미경은 연 1회 이상 optical alignment와 mechanical movement에 대한 전문가의 예방점검 및 수리를 받아야 한다."
    },
    {
      "code": "40.507.020",
      "type": "B",
      "points": 1,
      "question": "필요시 사용 가능한 생물안전작업대가 있는가?",
      "guidance": "없음"
    },
    {
      "code": "40.507.040",
      "type": "B",
      "points": 8,
      "question": "생물안전작업대는 연 1회 이상 필터의 성능과 유속 등을 점검하는가?",
      "guidance": "HEPA 필터는 0.3 ㎛ 크기 입자의 99.97% 이상을 제거할 수 있어야 한다.\n유속이란 캐비닛 안으로 유입되는 공기의 속도를 말하는 것으로 문을 열고 작업대 안에서 측정한다. 결과의 일관성을 유지하기 위해 항상 같은 위치에서 측정하도록 위치를 표시해 둔다.\n유속은 class I 형은 0.38 m/sec, class II 형은 0.38 m/sec (type A1) 또는 0.51 m/sec (type A2, type B1, type B2) 이상이어야 한다.\n점검일정이 계획되어 있어야 한다.\n점검자 및 검사실 담당자의 서명이 포함된 점검 기록지가 있어야 한다."
    },
    {
      "code": "40.509.040",
      "type": "B",
      "points": 1,
      "question": "pH 측정기의 보정에는 증명된 양질의 완충액을 사용하는가?",
      "guidance": "없음"
    },
    {
      "code": "40.600.020",
      "type": "B",
      "points": 1,
      "question": "각 장비에 대한 지침서가 있는가?",
      "guidance": "지침서는 검사장비의 켜기, 작동, 끄기 및 기능점검에 대한 내용을 포함해야 한다.\n검사담당자가 쉽게 열람할 수 있어야 한다.\n해당되는 장비는 다음과 같다.\n(1) 혈액은행용 냉장고\n(2) 혈액은행용 냉동고\n(3) 혈소판 교반장치\n(4) 해동용 온수조\n(5) 혈액성분채집기\n(6) serofuge\n(7) 혈구세척기\n(8) 헌혈용 혈액혼합기\n(9) 혈액은행검사 자동화장비"
    },
    {
      "code": "40.600.040",
      "type": "B",
      "points": 1,
      "question": "각 검사장비의 기능 점검 및 유지보수 체계가 있는지를 확인하는 기록이 있는가?",
      "guidance": "모든 검사장비에 대해 장비점검 및 유지보수 기록부가 있는지 확인한다.\n장비점검 또는 유지보수 기록부에는 장비 회사에서 추천하는 정기 및 비정기 점검 사항과 각 검사실에서 필요에 따라 정한 사항들이 시행되고 기록되어야 한다. 이는 전기적, 기계적, 조작상의 점검 등을 모두 포함한다.\n점검 절차와 빈도는 제조사의 지침을 따른다.\n기능점검 사항의 허용한계가 있는 경우 장비 또는 장비의 모니터 근처에 이를 명시한 문서가 비치되어 있어야 한다.\n장부를 확인하며 장비 작동시 점검 사항을 기록하는지 확인한다. 또한 문제가 발견되었을 때 반드시 기록하는지, 수정 조치 사항을 정확히 기록하는지 확인한다.\n장비에 이상이 생긴 경우 대응방법에는 장비회사 및 담당자 연락처, 보수시 필요한 조치 등이 구체적으로 명시되어 있어야 한다.\n혈액보관냉장고, 냉동고 및 해동장비에 이상이 생겼을 때 보관된 혈액에 대한 대응 방법이 문서화되어 있어야 한다.\n해동용 온수조의 유지보수에는 구체적인 수질 관리 방안이 포함되"
    },
    {
      "code": "40.600.140",
      "type": "B",
      "points": 1,
      "question": "각 검사장비의 수리지침서 (troubleshooting)가 있는가?",
      "guidance": "모든 기기별로 제조회사의 수리 지침서 또는 서비스 지침서가 마련되어 있어야 한다."
    },
    {
      "code": "40.600.160",
      "type": "B",
      "points": 1,
      "question": "각 검사장비의 수리 및 서비스 내역 장부가 있는가?",
      "guidance": "수리 및 서비스에 대한 장부가 장비 근처에 비치되어 있으며, 성실히 기록되는지 확인한다. 만일 장비가 단 한번의 고장도 없었다 하더라도 최소한 연 1회 정도는 제조회사의 서비스 또는 자체 점검을 실시하여야 한다.\n모든 기기에 대하여 기록이 있어야 하는 것은 아니지만 수리 및 서비스가 있는 경우에는 반드시 기록하도록 한다."
    },
    {
      "code": "40.603.402",
      "type": "B",
      "points": 1,
      "question": "응집과 용혈에 대한 판정기준이 정해져 있는가?",
      "guidance": "없음"
    }
  ]
}