{
  "field": "조직적합성검사",
  "chunk": 4,
  "total_chunks": 10,
  "items": [
    {
      "code": "70.504.040",
      "type": "B",
      "points": 2,
      "question": "검사실의 모든 일반 온도계는 설치 시 표준온도계로 점검한 후 사용하고 있는가?",
      "guidance": "· 일반 온도계는 표준온도계와 비교하여 연 1회 이상 주기적으로 점검한 기록이 있어야 한다. 기록이 없는 경\n우 ‘1점’을 감점한다.\n· 일반 온도계는 사용하는 전 범위에 걸쳐 비교, 점검하여야 한다.\n· 일반 온도계에는 고유번호, 점검필증, 사용처(이는 점검온도 범위가 국한될 때 필요하다.) 및 수정사항이 부\n착되어 있어야 한다. 각 온도계별로 별도의 사항이 부착되어 식별이 용이하지 않은 경우 ‘1점’을 감점한다.\n· 기기에 내장된 디지털 온도계 역시 점검되어야 한다."
    },
    {
      "code": "70.504.100",
      "type": "B",
      "points": 1,
      "question": "일반장비 및 검사장비의 온도점검이 매일 또는 검 사시행일마다 이루어지고 있는가?",
      "guidance": "· 온도관련 기기에는 다음 장비가 포함된다.\n(1) 수조\n(2) Dry baths (heating blocks)\n(3) 인큐베이터\n(4) 오븐\n(5) 냉장고\n(6) 냉동고\n· 각 장비별로 온도 점검표를 확인한다. 이러한 온도 점검표처럼 매일 기록해야 하는 경우 해당 기기에 기록부\n를 붙여두고 기록한 후 매월 장부로 이동하여 보관하는 방법이 권장된다.\n· 온도 점검표는 반드시 수기로 기록되어야 한다(단, 지속적 모니터링 시스템으로서 자동기록하는 경우, 수기로\n기록할 필요가 없다.).\n· 온도 점검표에는 실제 측정된 온도와 표준온도계와의 차이가 반영된 온도가 표시되어야 한다."
    },
    {
      "code": "70.504.300",
      "type": "B",
      "points": 1,
      "question": "모든 온도관련 기기(냉장고, 냉동고 등)에는 온도의 허용범위가 정해져 있는가?",
      "guidance": "· 장비별 온도 점검표에 허용범위가 표시되어 있어야 한다.\n· 온도관련 기기의 온도가 허용범위를 벗어났을 경우, 취하여야 할 조치 등에 관한 지침 및 시행기록이 있어야\n한다(수정조치 내용에는 냉장고나 냉동고에 보관하였던 정도관리물질, 시약, 보정물질 등에 대한 평가기록이\n있어야 한다.).\n· 제조사의 규정에 맞게 시약이나 검체 상태가 영향을 받지 않는 범위내에서 온도가 유지되고 기록되고 있는지\n에 대한 지침과 기록을 확인한다."
    },
    {
      "code": "70.504.361",
      "type": "B",
      "points": 2,
      "question": "세포를 액체질소탱크에 냉동 보관하는 경우, 적정한 세포 보관 온도를 유지할 수 있도록 액 체질소의 양을 주기적으로 모니터링하는가? 설명  없음 3. 현미경",
      "guidance": ""
    },
    {
      "code": "70.506.020",
      "type": "B",
      "points": 1,
      "question": "렌즈가 저배율, 고배율 등에서 깨끗하고 정확하게 보이는 지에 대한 정기적인 점검기록부가 있는가?",
      "guidance": "· 현미경 점검 기록부를 확인한다. 현미경은 연 1회 이상 optical alignment와 mechanical movement에\n대한 전문가의 예방점검 및 수리를 받아야 한다."
    },
    {
      "code": "70.506.200",
      "type": "B",
      "points": 1,
      "question": "형광현미경의 광원 강도가 검사에적합한지 모니터하고, 검사 목적에 맞는 필터와 슬라이드를 사용하는가?",
      "guidance": "· 광원 강도의 적합성을 모니터하는 절차가 있어야 한다. 예로, 벌브(bulb) 사용 시간을 추적하고, 해당하는 경\n우 제조사의 권장 사항에 따라 벌브 사용을 제한하는 절차가 있다.\n설명  절차에 따라 형광현미경을 모니터한 기록이 있어야 한다.\n· 검사지침서에는 형광현미경에 사용하는 여기(excitation) 필터와 방출(emission) 필터를 반드시 명시하고,\n적합한 필터와 슬라이드 사용에 관한 검사 절차가 문서화되어 있어야 한다.\n4. 생물학적 안전상자"
    },
    {
      "code": "70.507.020",
      "type": "B",
      "points": 1,
      "question": "필요시 사용 가능한 생물안전작업 대가 있는가? 설명  없음",
      "guidance": ""
    },
    {
      "code": "70.507.040",
      "type": "B",
      "points": 8,
      "question": "생물안전작업대는 연 1회 이상 필터의 성능과 유속 등을 점검하는가?",
      "guidance": "· HEPA 필터는 0.3㎛ 크기 입자의 99.97% 이상을 제거할 수 있어야 한다.\n· 유속이란 캐비닛 안으로 유입되는 공기의 속도를 말하는 것으로 문을 열고 작업대 안에서 측정한다. 결과의\n일관성을 유지하기 위해 항상 같은 위치에서 측정하도록 위치를 표시해 둔다.\n설명  유속은 class I 형은 0.38 m/sec, class II 형은 0.38 m/sec (type A1) 또는 0.51 m/sec (type A2,\ntype B1, type B2) 이상이어야 한다.\n· 점검일정이 계획되어 있어야 한다.\n· 점검자 및 검사실 담당자의 서명이 포함된 점검 기록지가 있어야 한다.\n5. 후드"
    },
    {
      "code": "70.508.020",
      "type": "B",
      "points": 1,
      "question": "휘발성 화학물질을 이용한 검사 시 후드를 사용하는가?",
      "guidance": "· 검사실에서 사용하는 휘발성 화학물질의 예로는 에테르(ether), 포르말린(formalin) 및 톨루엔(toluene) 등\n이 있다."
    },
    {
      "code": "70.508.040",
      "type": "B",
      "points": 4,
      "question": "후드는 정해진 공기 유속을 유지 할 수 있도록 일 년에 한 번씩 점검 받는가? 설명  없음 7 검사수행 및 장비 운용 1. 일반사항 ‘유세포분석기를 이용한 교차시험’을 시행한다면 조직적합성검사와 유세포검사 분야 심사를 모두 받아야 한다. 문항 기본B 70.600.020 각 장비에 대한 지침서가 있는가?",
      "guidance": "· 지침서는 검사장비의 켜기, 작동, 끄기 및 기능점검에 대한 내용을 포함해야 한다.\n· 검사담당자가 쉽게 열람할 수 있어야 한다."
    }
  ]
}